{"tenant_id": "0342730699fa48ad884e6912d15ff316", "server_usages": [{"hours": 0.028333333333333332, "flavor": "rally_verify_267efb0f_4huGdMfn", "instance_id": "9bad4f49-4c6b-4c2d-bafe-cb1cfe838705", "name": "tempest-MigrationsAdminTest-server-495141005", "tenant_id": "0342730699fa48ad884e6912d15ff316", "memory_mb": 128, "local_gb": 5, "vcpus": 1, "started_at": "2022-01-27T20:16:56.000000", "ended_at": "2022-01-27T20:18:38.000000", "state": "terminated", "uptime": 102}, {"hours": 0.001388888888888889, "flavor": "tempest-test_resize_flavor_-1137441560", "instance_id": "b93b553f-db9d-457a-9ae4-a1c19bc98608", "name": "tempest-MigrationsAdminTest-server-2045614650", "tenant_id": "0342730699fa48ad884e6912d15ff316", "memory_mb": 64, "local_gb": 5, "vcpus": 1, "started_at": "2022-01-27T20:18:29.000000", "ended_at": "2022-01-27T20:18:34.000000", "state": "terminated", "uptime": 5}], "total_local_gb_usage": 0.1486111111111111, "total_vcpus_usage": 0.02972222222222222, "total_memory_mb_usage": 3.7155555555555555, "total_hours": 0.02972222222222222, "start": "2022-01-27T00:00:00.000000", "stop": "2022-01-28T00:00:00.000000"}
